[
  {
    "id": "TRX-0051",
    "data": "2023-02-09",
    "valor": 34.51,
    "conta_origem": "52714-5",
    "conta_destino": "95906-5",
    "tipo": "transferencia",
    "status": "falha"
  },
  {
    "id": "TRX-0052",
    "data": "2023-02-12",
    "valor": 3583.15,
    "conta_origem": "72178-5",
    "conta_destino": "62120-0",
    "tipo": "deposito",
    "status": "completo"
  },
  {
    "id": "TRX-0053",
    "data": "2023-02-14",
    "valor": 9180.63,
    "conta_origem": "36329-4",
    "conta_destino": "26185-3",
    "tipo": "saque",
    "status": "pendente"
  },
  {
    "id": "TRX-0054",
    "data": "2023-02-02",
    "valor": 4745.43,
    "conta_origem": "79512-4",
    "conta_destino": "85546-6",
    "tipo": "deposito",
    "status": "falha"
  },
  {
    "id": "TRX-0055",
    "data": "2023-02-26",
    "valor": 5748.45,
    "conta_origem": "72887-8",
    "conta_destino": "55651-0",
    "tipo": "deposito",
    "status": "falha"
  },
  {
    "id": "TRX-0056",
    "data": "2023-02-14",
    "valor": 7538.2,
    "conta_origem": "27242-9",
    "conta_destino": "81150-0",
    "tipo": "saque",
    "status": "falha"
  },
  {
    "id": "TRX-0057",
    "data": "2023-02-02",
    "valor": 4286.2,
    "conta_origem": "46202-0",
    "conta_destino": "75751-3",
    "tipo": "saque",
    "status": "falha"
  },
  {
    "id": "TRX-0058",
    "data": "2023-02-10",
    "valor": 8136.32,
    "conta_origem": "61074-8",
    "conta_destino": "45210-6",
    "tipo": "saque",
    "status": "pendente"
  },
  {
    "id": "TRX-0059",
    "data": "2023-02-23",
    "valor": 8285.55,
    "conta_origem": "71609-9",
    "conta_destino": "86386-7",
    "tipo": "pagamento",
    "status": "pendente"
  },
  {
    "id": "TRX-0060",
    "data": "2023-02-07",
    "conta_origem": "10399-1",
    "conta_destino": "50659-6",
    "tipo": "transferencia",
    "status": "completo"
  },
  {
    "id": "TRX-0061",
    "data": "2023-02-06",
    "valor": 1368.3,
    "conta_origem": "70134-7",
    "conta_destino": "94345-2",
    "tipo": "pagamento",
    "status": "falha"
  },
  {
    "id": "TRX-0062",
    "data": "2023-02-26",
    "valor": 3468.23,
    "conta_origem": "29399-1",
    "conta_destino": "51193-5",
    "tipo": "pagamento",
    "status": "falha"
  },
  {
    "id": "TRX-0063",
    "data": "2023-02-28",
    "valor": 656.17,
    "conta_origem": "52741-0",
    "conta_destino": "74956-6",
    "tipo": "transferencia",
    "status": "falha"
  },
  {
    "id": "TRX-0064",
    "data": "2023-02-16",
    "valor": 7416.69,
    "conta_origem": "20394-3",
    "conta_destino": "83932-1",
    "tipo": "pagamento",
    "status": "falha"
  },
  {
    "id": "TRX-0065",
    "data": "2023-02-23",
    "valor": 4969.47,
    "conta_origem": "32261-6",
    "conta_destino": "85165-4",
    "tipo": "saque",
    "status": "pendente"
  },
  {
    "id": "TRX-0066",
    "data": "2023-02-28",
    "valor": 6856.74,
    "conta_origem": "86188-3",
    "conta_destino": "28685-1",
    "tipo": "transferencia",
    "status": "completo"
  },
  {
    "id": "TRX-0067",
    "data": "2023-02-17",
    "valor": 5062.99,
    "conta_origem": "50589-2",
    "conta_destino": "85769-2",
    "tipo": "pagamento",
    "status": "falha"
  },
  {
    "id": "TRX-0068",
    "data": "2023-02-28",
    "valor": 3978.6,
    "conta_origem": "46671-0",
    "conta_destino": "40870-6",
    "tipo": "saque",
    "status": "pendente"
  },
  {
    "id": "TRX-0069",
    "data": "2023-02-01",
    "valor": 9059.04,
    "conta_origem": "98367-5",
    "conta_destino": "69103-4",
    "tipo": "pagamento",
    "status": "pendente"
  },
  {
    "id": "TRX-0070",
    "data": "2023-02-17",
    "valor": 8962.58,
    "conta_origem": "53932-9",
    "conta_destino": "77811-5",
    "tipo": "deposito",
    "status": "pendente"
  },
  {
    "id": "TRX-0071",
    "data": "2023-02-10",
    "conta_origem": "39606-8",
    "conta_destino": "90719-1",
    "tipo": "deposito",
    "status": "completo"
  },
  {
    "id": "TRX-0072",
    "data": "2023-02-03",
    "valor": 8145.46,
    "conta_origem": "48450-0",
    "conta_destino": "55847-6",
    "tipo": "deposito",
    "status": "pendente"
  },
  {
    "id": "TRX-0073",
    "data": "2023-02-03",
    "valor": 7384.95,
    "conta_origem": "45395-6",
    "conta_destino": "16547-2",
    "tipo": "operacao-desconhecida",
    "status": "falha"
  },
  {
    "id": "TRX-0074",
    "data": "2023-02-14",
    "valor": 8169.09,
    "conta_origem": "52699-8",
    "conta_destino": "51152-5",
    "tipo": "saque",
    "status": null
  },
  {
    "id": "TRX-0075",
    "data": "2023-02-01",
    "valor": 8267.24,
    "conta_origem": "85822-6",
    "conta_destino": "20091-3",
    "tipo": "saque",
    "status": "completo"
  },
  {
    "id": "TRX-0076",
    "data": "2023-02-11",
    "valor": 5979.05,
    "conta_origem": "24839-9",
    "conta_destino": "58529-1",
    "tipo": "deposito",
    "status": "pendente"
  },
  {
    "id": "TRX-0077",
    "data": "2023-02-27",
    "valor": 9809.49,
    "conta_origem": "39734-1",
    "conta_destino": "51782-8",
    "tipo": "deposito",
    "status": "completo"
  },
  {
    "id": "TRX-0078",
    "data": "2023-02-10",
    "valor": 1414.45,
    "conta_origem": "58327-5",
    "conta_destino": "36134-9",
    "tipo": "saque",
    "status": "completo"
  },
  {
    "id": "TRX-0079",
    "data": "2023-02-12",
    "valor": 616.84,
    "conta_origem": "75138-9",
    "conta_destino": "82676-9",
    "tipo": "deposito",
    "status": "falha"
  },
  {
    "id": "TRX-0080",
    "data": "2023-02-05",
    "valor": "8230.46",
    "conta_origem": "73410-5",
    "conta_destino": "20877-6",
    "tipo": "deposito",
    "status": "completo"
  },
  {
    "id": "TRX-0081",
    "data": "2023-02-06",
    "valor": 350.23,
    "conta_origem": "77171-0",
    "conta_destino": "53618-4",
    "tipo": "transferencia",
    "status": "completo"
  },
  {
    "id": "TRX-0082",
    "data": "2023-02-05",
    "valor": 2111.62,
    "conta_origem": "47830-0",
    "conta_destino": "77585-3",
    "tipo": "pagamento",
    "status": "pendente"
  },
  {
    "id": "TRX-0083",
    "data": "2023-02-13",
    "valor": -863.15,
    "conta_origem": "49356-9",
    "conta_destino": "50300-9",
    "tipo": "pagamento",
    "status": "falha"
  },
  {
    "id": "TRX-0084",
    "data": "2023-02-02",
    "valor": 7435.69,
    "conta_origem": "94577-7",
    "conta_destino": "36362-9",
    "tipo": "saque",
    "status": "falha"
  },
  {
    "id": "TRX-0085",
    "data": "2023-02-20",
    "valor": 351.46,
    "conta_origem": "60538-1",
    "conta_destino": "77714-8",
    "tipo": "deposito",
    "status": "falha"
  },
  {
    "id": "TRX-0086",
    "data": "2023-02-11",
    "valor": 566.2,
    "conta_origem": "95159-1",
    "conta_destino": "67266-3",
    "tipo": "transferencia",
    "status": "pendente"
  },
  {
    "id": "TRX-0087",
    "data": "2023-02-24",
    "valor": 66.17,
    "conta_origem": "37823-0",
    "conta_destino": "86275-3",
    "tipo": "deposito",
    "status": "pendente"
  },
  {
    "id": "TRX-0088",
    "data": "2023-02-21",
    "valor": 3320.46,
    "conta_origem": "63760-8",
    "conta_destino": "40345-7",
    "tipo": "saque",
    "status": "pendente"
  },
  {
    "id": "TRX-0089",
    "data": "2023-02-17",
    "valor": -7473.31,
    "conta_origem": "24680-5",
    "conta_destino": "86719-7",
    "tipo": "transferencia",
    "status": "pendente"
  },
  {
    "id": "TRX-0090",
    "data": "2023-02-11",
    "valor": -6792.65,
    "conta_origem": "23418-8",
    "conta_destino": "46827-4",
    "tipo": "pagamento",
    "status": "completo"
  },
  {
    "id": "TRX-0091",
    "data": "2023-02-20",
    "valor": 2833.95,
    "conta_origem": "32238-9",
    "conta_destino": "64697-7",
    "tipo": "transferencia",
    "status": "pendente"
  },
  {
    "id": "TRX-0092",
    "data": "2023-02-23",
    "valor": 8782.1,
    "conta_origem": "90609-1",
    "conta_destino": "73338-7",
    "tipo": "deposito",
    "status": "falha"
  },
  {
    "id": "TRX-0093",
    "data": "2023-02-26",
    "valor": 7367.63,
    "conta_origem": "70975-3",
    "conta_destino": "66153-1",
    "tipo": "transferencia",
    "status": "falha"
  },
  {
    "id": "TRX-0094",
    "data": "2023-02-20",
    "valor": 7466.2,
    "conta_origem": "56733-4",
    "conta_destino": "33823-0",
    "tipo": "deposito",
    "status": "pendente"
  },
  {
    "id": "TRX-0095",
    "data": "2023-02-26",
    "valor": 9413.13,
    "conta_origem": "13062-8",
    "conta_destino": "34773-7",
    "tipo": "saque",
    "status": "completo"
  },
  {
    "id": "TRX-0096",
    "data": "2023-02-14",
    "valor": 3757.48,
    "conta_origem": "37702-6",
    "conta_destino": "74918-0",
    "tipo": "saque",
    "status": "falha"
  },
  {
    "id": "TRX-0097",
    "data": "2023-02-19",
    "valor": 7993.81,
    "conta_origem": "79821-6",
    "conta_destino": "27149-4",
    "tipo": "pagamento",
    "status": "completo"
  },
  {
    "id": "TRX-0098",
    "data": "data-invalida",
    "valor": 7286.39,
    "conta_origem": "60884-0",
    "conta_destino": "28917-2",
    "tipo": "transferencia",
    "status": "pendente"
  },
  {
    "id": "TRX-0099",
    "data": "2023-02-11",
    "valor": 7037.55,
    "conta_origem": "60750-9",
    "conta_destino": "99931-8",
    "tipo": "deposito",
    "status": "falha"
  },
  {
    "id": "TRX-0100",
    "data": "2023-02-19",
    "valor": 570.99,
    "conta_origem": "97641-6",
    "conta_destino": "85287-3",
    "tipo": "transferencia",
    "status": "completo"
  }
]